thinqconnect_mcp/__init__.py
thinqconnect_mcp/prompts.py
thinqconnect_mcp/server.py
thinqconnect_mcp/tools.py
thinqconnect_mcp-0.0.5.dist-info/licenses/LICENSE
thinqconnect_mcp-0.0.5.dist-info/METADATA
thinqconnect_mcp-0.0.5.dist-info/WHEEL
thinqconnect_mcp-0.0.5.dist-info/entry_points.txt
thinqconnect_mcp-0.0.5.dist-info/top_level.txt
thinqconnect_mcp-0.0.5.dist-info/RECORD
