Metadata-Version: 2.4
Name: thinqconnect-mcp
Version: 0.0.5
Summary: ThinQ Connect MCP
Author-email: ThinQ Connect <thinq-connect@lge.com>
License:                                  Apache License
Project-URL: Homepage, https://github.com/thinq-connect/thinqconnect-mcp
Classifier: Programming Language :: Python :: 3
Classifier: License :: OSI Approved :: Apache Software License
Classifier: Operating System :: OS Independent
Classifier: Programming Language :: Python :: 3.11
Requires-Python: >=3.11
License-File: LICENSE
Requires-Dist: thinqconnect
Requires-Dist: python-dotenv==1.1.1
Requires-Dist: mcp==1.12.3
Requires-Dist: aiohttp==3.12.15
Dynamic: license-file
